binary_semantic_cache.libs/libgcc_s-a04fdf82.so.1
binary_semantic_cache-1.0.1.dist-info/WHEEL
binary_semantic_cache-1.0.1.dist-info/entry_points.txt
binary_semantic_cache-1.0.1.dist-info/METADATA
binary_semantic_cache-1.0.1.dist-info/RECORD
binary_semantic_cache-1.0.1.dist-info/licenses/LICENSE
binary_semantic_cache/binary_semantic_cache_rs.cpython-311-x86_64-linux-musl.so
binary_semantic_cache/config.py
binary_semantic_cache/__init__.py
binary_semantic_cache/embeddings/ollama_backend.py
binary_semantic_cache/embeddings/openai_backend.py
binary_semantic_cache/embeddings/__init__.py
binary_semantic_cache/embeddings/base.py
binary_semantic_cache/proxy/server.py
binary_semantic_cache/proxy/__init__.py
binary_semantic_cache/tools/migrate.py
binary_semantic_cache/tools/__init__.py
binary_semantic_cache/embedding/__init__.py
binary_semantic_cache/core/similarity.py
binary_semantic_cache/core/eviction.py
binary_semantic_cache/core/encoder.py
binary_semantic_cache/core/cache.py
binary_semantic_cache/core/__init__.py
