Metadata-Version: 2.4
Name: binary-semantic-cache
Version: 1.0.1
Classifier: Development Status :: 5 - Production/Stable
Classifier: Intended Audience :: Developers
Classifier: License :: OSI Approved :: MIT License
Classifier: Operating System :: OS Independent
Classifier: Programming Language :: Python :: 3
Classifier: Programming Language :: Python :: 3.10
Classifier: Programming Language :: Python :: 3.11
Classifier: Programming Language :: Python :: 3.12
Classifier: Programming Language :: Rust
Classifier: Topic :: Scientific/Engineering :: Artificial Intelligence
Classifier: Typing :: Typed
Requires-Dist: numpy>=1.24
Requires-Dist: numba>=0.58
Requires-Dist: pydantic>=2.0
Requires-Dist: pydantic-settings>=2.0
Requires-Dist: fastapi>=0.100 ; extra == 'proxy'
Requires-Dist: uvicorn>=0.23 ; extra == 'proxy'
Requires-Dist: httpx>=0.25 ; extra == 'proxy'
Requires-Dist: openai>=1.0 ; extra == 'openai'
Requires-Dist: tiktoken>=0.5 ; extra == 'openai'
Requires-Dist: tenacity>=8.0 ; extra == 'openai'
Requires-Dist: sentence-transformers>=2.2 ; extra == 'local'
Requires-Dist: pytest>=7.0 ; extra == 'dev'
Requires-Dist: pytest-asyncio>=0.21 ; extra == 'dev'
Requires-Dist: pytest-cov>=4.0 ; extra == 'dev'
Requires-Dist: mypy>=1.5 ; extra == 'dev'
Requires-Dist: ruff>=0.1 ; extra == 'dev'
Requires-Dist: black>=23.0 ; extra == 'dev'
Requires-Dist: maturin>=1.4 ; extra == 'dev'
Requires-Dist: binary-semantic-cache[proxy,openai,local,dev] ; extra == 'all'
Provides-Extra: proxy
Provides-Extra: openai
Provides-Extra: local
Provides-Extra: dev
Provides-Extra: all
License-File: LICENSE
Summary: High-performance semantic caching for LLM APIs using binary embeddings
Keywords: llm,cache,semantic,binary,embeddings,openai,api
Author-email: Matteo Panzeri <matteo1782@gmail.com>
Maintainer-email: Matteo Panzeri <matteo1782@gmail.com>
License-Expression: MIT
Requires-Python: >=3.10
Project-URL: Homepage, https://github.com/matte1782/binary_semantic_cache
Project-URL: Documentation, https://github.com/matte1782/binary_semantic_cache#readme
Project-URL: Repository, https://github.com/matte1782/binary_semantic_cache.git
